CHANGELOG.md
LICENSE
README.md
taiga_stats/__init__.py
taiga_stats/__main__.py
taiga_stats/commands.py
taiga_stats/config.py
taiga_stats/constants.py
taiga_stats/helpers.py
taiga_stats/parse_args.py
taiga_stats-1.6.0.dist-info/entry_points.txt
taiga_stats-1.6.0.dist-info/LICENSE
taiga_stats-1.6.0.dist-info/WHEEL
taiga_stats-1.6.0.dist-info/METADATA
taiga_stats-1.6.0.dist-info/RECORD
