Metadata-Version: 2.1
Name: taiga-stats
Version: 1.6.0
Summary: Generate statistics from Taiga and produce burnup diagrams, CFDs, dependency graphs and more.
Home-page: https://github.com/erikw/taiga-stats
License: BSD-3-Clause
Keywords: taiga,generator,stats,cfd,dependency graph
Author: Erik Westrup
Author-email: erik.westrup@gmail.com
Requires-Python: >=3.7,<3.10.0
Classifier: License :: OSI Approved :: BSD License
Classifier: Programming Language :: Python :: 3
Classifier: Programming Language :: Python :: 3.7
Classifier: Programming Language :: Python :: 3.8
Classifier: Programming Language :: Python :: 3.9
Classifier: Topic :: Software Development
Classifier: Topic :: Utilities
Requires-Dist: matplotlib (>=2.1.0,<3.0.0)
Requires-Dist: numpy (>=1.13.3,<2.0.0)
Requires-Dist: python-taiga (>=1.0.0,<2.0.0)
Requires-Dist: single-source (>=0.2,<0.4)
